pycdiscount/__init__.py
pycdiscount-0.3.5.dist-info/DESCRIPTION.rst
pycdiscount-0.3.5.dist-info/METADATA
pycdiscount-0.3.5.dist-info/RECORD
pycdiscount-0.3.5.dist-info/WHEEL
pycdiscount-0.3.5.dist-info/metadata.json
pycdiscount-0.3.5.dist-info/top_level.txt
