Metadata-Version: 2.0
Name: pycdiscount
Version: 0.3.5
Summary: A simple Python Wrapper for CDiscount API using Requests.
Home-page: https://github.com/wblondel/PythonCdiscountWrapper
Author: William Gerald Blondel
Author-email: contact@williamblondel.fr
License: GNU GPL
Platform: UNKNOWN
Classifier: Programming Language :: Python
Classifier: Development Status :: 4 - Beta
Classifier: Programming Language :: Python :: 3.4
Classifier: Programming Language :: Python :: 3.5
Classifier: Programming Language :: Python :: 3.6
Classifier: Topic :: Internet
Classifier: License :: OSI Approved :: GNU General Public License v3 (GPLv3)
Requires-Dist: requests
